[
{"price": "\u20b9 1.10 Cr", "title": ["\n\t            \t\t\n\t            \t\t\n\t\t\t\t\t\t\t\n\t\t\t\t\t\t\n\t            \t\t\n\t\t\t\t\t\t\t\n\t            \t\t\t\n\t            \t\t\t\n\t            \t\t\t\t\n\t\t\t            \t\t\n\t\t\t            \t\t\n\t\t\t            \t\t\n\t\t\t            \t\t\n\t            \t\t\t\n\t            \t\t\n\t\t\t\t\t\t\t", "\n\n\t\t\t\t\t\t\t\n\t\t\t\t\t\t\t\t\n\t\t            \t\t\t\t for Sale\n\t\t            \t\t\t\n\t\t\t\t\t\t\t\t\n\t\t\t\t\t\t\t\t\n\t\t\t\t\t\t\t\t\n\t\t\t\t\t\t\t\n\n\t\t\t\t\t\t\t\n\t\t\t\t\t\t\t\t\n\t\t\t\t\t\t\t\t\n\t\t\t\t\t\t\t\t\n\t\t\t\t\t\t\t\n\t\t                \t\n\t\t                \t\t\n\t\t                \t\t\t\tin   Yapral \n\t\t                \t\t\n\t\t\t\t\t\t           \n\t         \t\t    \t\t\n\t\t           \t\t\t\n\t\t           \t\t\t\n                   "], "bhk": "\n\t\t\t            \t\t\n\t\t\t            \t\t\t\n\t\t\t            \t\t\t\t3 BHK Flat\n\t\t\t            \t\t\t\n\t\t\t            \t\t\t\n\t\t\t            \t\t\n\t\t\t            \t\t\n\t\t\t            \t", "societyName": "Patels Bright View", "moreData": [["super area", "2570\u00a0sqft"], ["status", "Ready to Move"], ["floor", "5 out of 5 floors"], ["transaction", "New Property"], ["furnishing", "Semi-Furnished"], ["car parking", "1 Covered"], ["bathroom", "4"]]},
{"price": "\u20b9 1.58 Cr", "title": ["\n\t            \t\t\n\t            \t\t\n\t            \t\t\n\t\t\t\t\t\t\t\n\t            \t\t\t\n\t            \t\t\t\n\t            \t\t\t\t\n\t\t\t            \t\t\n\t\t\t            \t\t\n\t\t\t            \t\t\n\t\t\t            \t\t\n\t            \t\t\t\n\t            \t\t\n\t\t\t\t\t\t\t", "\n\n\t\t\t\t\t\t\t\n\t\t\t\t\t\t\t\t\n\t\t            \t\t\t\t for Sale\n\t\t            \t\t\t\n\t\t\t\t\t\t\t\t\n\t\t\t\t\t\t\t\t\n\t\t\t\t\t\t\t\t\n\t\t\t\t\t\t\t\n\n\t\t\t\t\t\t\t\n\t\t\t\t\t\t\t\t\n\t\t\t\t\t\t\t\t\n\t\t\t\t\t\t\t\t\n\t\t\t\t\t\t\t\n\t\t                \t\n\t\t                \t\t\n\t\t                \t\t\t\tin   Gachibowli, Outer Ring Road \n\t\t                \t\t\n\t\t\t\t\t\t           \n\t         \t\t    \t\t\n\t\t           \t\t\t\n\t\t           \t\t\t\n                   "], "bhk": "\n\t\t\t            \t\t\n\t\t\t            \t\t\t\n\t\t\t            \t\t\t\t3 BHK Flat\n\t\t\t            \t\t\t\n\t\t\t            \t\t\t\n\t\t\t            \t\t\n\t\t\t            \t\t\n\t\t\t            \t", "societyName": "Rajapushpa Eterna", "moreData": [["super area", "2360\u00a0sqft"], ["status", "\n\t\t\t\t\t\t\t\tPossession by Dec '21\n\t\t\t\t\t\t\t"], ["transaction", "New Property"], ["furnishing", "Unfurnished"], ["car parking", "1 Covered"], ["bathroom", "3"]]},
{"price": "\u20b9 1.84 Cr", "title": ["\n\t            \t\t\n\t            \t\t\n\t            \t\t\n\t\t\t\t\t\t\t\n\t            \t\t\t\n\t            \t\t\t\n\t            \t\t\t\t\n\t\t\t            \t\t\n\t\t\t            \t\t\n\t\t\t            \t\t\n\t\t\t            \t\t\n\t            \t\t\t\n\t            \t\t\n\t\t\t\t\t\t\t", "\n\n\t\t\t\t\t\t\t\n\t\t\t\t\t\t\t\t\n\t\t            \t\t\t\t for Sale\n\t\t            \t\t\t\n\t\t\t\t\t\t\t\t\n\t\t\t\t\t\t\t\t\n\t\t\t\t\t\t\t\t\n\t\t\t\t\t\t\t\n\n\t\t\t\t\t\t\t\n\t\t\t\t\t\t\t\t\n\t\t\t\t\t\t\t\t\n\t\t\t\t\t\t\t\t\n\t\t\t\t\t\t\t\n\t\t                \t\n\t\t                \t\t\n\t\t                \t\t\t\tin   Banjara Hills, NH  9 \n\t\t                \t\t\n\t\t\t\t\t\t           \n\t         \t\t    \t\t\n\t\t           \t\t\t\n\t\t           \t\t\t\n                   "], "bhk": "\n\t\t\t            \t\t\n\t\t\t            \t\t\t\n\t\t\t            \t\t\t\t3 BHK Flat\n\t\t\t            \t\t\t\n\t\t\t            \t\t\t\n\t\t\t            \t\t\n\t\t\t            \t\t\n\t\t\t            \t", "societyName": "Dukes Galaxy", "moreData": [["super area", "1980\u00a0sqft"], ["status", "Ready to Move"], ["transaction", "New Property"], ["furnishing", "Unfurnished"], ["car parking", "2 Covered"], ["bathroom", "3"]]},
{"price": "\u20b9 1.26 Cr", "title": ["\n\t            \t\t\n\t            \t\t\n\t            \t\t\n\t\t\t\t\t\t\t\n\t            \t\t\t\n\t            \t\t\t\n\t            \t\t\t\t\n\t\t\t            \t\t\n\t\t\t            \t\t\n\t\t\t            \t\t\n\t\t\t            \t\t\n\t            \t\t\t\n\t            \t\t\n\t\t\t\t\t\t\t", "\n\n\t\t\t\t\t\t\t\n\t\t\t\t\t\t\t\t\n\t\t            \t\t\t\t for Sale\n\t\t            \t\t\t\n\t\t\t\t\t\t\t\t\n\t\t\t\t\t\t\t\t\n\t\t\t\t\t\t\t\t\n\t\t\t\t\t\t\t\n\n\t\t\t\t\t\t\t\n\t\t\t\t\t\t\t\t\n\t\t\t\t\t\t\t\t\n\t\t\t\t\t\t\t\t\n\t\t\t\t\t\t\t\n\t\t                \t\n\t\t                \t\t\n\t\t                \t\t\t\tin   Suchitra Circle \n\t\t                \t\t\n\t\t\t\t\t\t           \n\t         \t\t    \t\t\n\t\t           \t\t\t\n\t\t           \t\t\t\n                   "], "bhk": "\n\t\t\t            \t\t\n\t\t\t            \t\t\t\n\t\t\t            \t\t\t\t3 BHK Flat\n\t\t\t            \t\t\t\n\t\t\t            \t\t\t\n\t\t\t            \t\t\n\t\t\t            \t\t\n\t\t\t            \t", "societyName": "Sri Ram Garden By Jains", "moreData": [["super area", "1950\u00a0sqft"], ["status", "\n\t\t\t\t\t\t\t\tPossession by Dec '21\n\t\t\t\t\t\t\t"], ["transaction", "New Property"], ["furnishing", "Unfurnished"], ["car parking", "2 Covered"], ["bathroom", "3"]]},
{"price": "\u20b9 65.5 Lac", "title": ["\n\t            \t\t\n\t            \t\t\n\t            \t\t\n\t\t\t\t\t\t\t\n\t            \t\t\t\n\t            \t\t\t\n\t            \t\t\t\t\n\t\t\t            \t\t\n\t\t\t            \t\t\n\t\t\t            \t\t\n\t\t\t            \t\t\n\t            \t\t\t\n\t            \t\t\n\t\t\t\t\t\t\t", "\n\n\t\t\t\t\t\t\t\n\t\t\t\t\t\t\t\t\n\t\t            \t\t\t\t for Sale\n\t\t            \t\t\t\n\t\t\t\t\t\t\t\t\n\t\t\t\t\t\t\t\t\n\t\t\t\t\t\t\t\t\n\t\t\t\t\t\t\t\n\n\t\t\t\t\t\t\t\n\t\t\t\t\t\t\t\t\n\t\t\t\t\t\t\t\t\n\t\t\t\t\t\t\t\t\n\t\t\t\t\t\t\t\n\t\t                \t\n\t\t                \t\t\n\t\t                \t\t\t\tin   Upparpally, Hyderabad Expressway \n\t\t                \t\t\n\t\t\t\t\t\t           \n\t         \t\t    \t\t\n\t\t           \t\t\t\n\t\t           \t\t\t\n                   "], "bhk": "\n\t\t\t            \t\t\n\t\t\t            \t\t\t\n\t\t\t            \t\t\t\t2 BHK Flat\n\t\t\t            \t\t\t\n\t\t\t            \t\t\t\n\t\t\t            \t\t\n\t\t\t            \t\t\n\t\t\t            \t", "societyName": "Theme Vista", "moreData": [["super area", "1310\u00a0sqft"], ["transaction", "New Property"], ["furnishing", "Unfurnished"], ["bathroom", "2"]]},
{"price": "\u20b9 1.28 Cr", "title": ["\n\t            \t\t\n\t            \t\t\n\t            \t\t\n\t\t\t\t\t\t\t\n\t            \t\t\t\n\t            \t\t\t\n\t            \t\t\t\t\n\t\t\t            \t\t\n\t\t\t            \t\t\n\t\t\t            \t\t\n\t\t\t            \t\t\n\t            \t\t\t\n\t            \t\t\n\t\t\t\t\t\t\t", "\n\n\t\t\t\t\t\t\t\n\t\t\t\t\t\t\t\t\n\t\t            \t\t\t\t for Sale\n\t\t            \t\t\t\n\t\t\t\t\t\t\t\t\n\t\t\t\t\t\t\t\t\n\t\t\t\t\t\t\t\t\n\t\t\t\t\t\t\t\n\n\t\t\t\t\t\t\t\n\t\t\t\t\t\t\t\t\n\t\t\t\t\t\t\t\t\n\t\t\t\t\t\t\t\t\n\t\t\t\t\t\t\t\n\t\t                \t\n\t\t                \t\t\n\t\t                \t\t\t\tin   Hitech City \n\t\t                \t\t\n\t\t\t\t\t\t           \n\t         \t\t    \t\t\n\t\t           \t\t\t\n\t\t           \t\t\t\n                   "], "bhk": "\n\t\t\t            \t\t\n\t\t\t            \t\t\t\n\t\t\t            \t\t\t\t3 BHK Flat\n\t\t\t            \t\t\t\n\t\t\t            \t\t\t\n\t\t\t            \t\t\n\t\t\t            \t\t\n\t\t\t            \t", "societyName": "Vishnu Vistara", "moreData": [["super area", "1890\u00a0sqft"], ["status", "Ready to Move"], ["transaction", "New Property"], ["furnishing", "Unfurnished"], ["car parking", "2 Covered"], ["bathroom", "3"], ["ownership", "Freehold"]]},
{"price": "\u20b9 1.54 Cr", "title": ["\n\t            \t\t\n\t            \t\t\n\t            \t\t\n\t\t\t\t\t\t\t\n\t            \t\t\t\n\t            \t\t\t\n\t            \t\t\t\t\n\t\t\t            \t\t\n\t\t\t            \t\t\n\t\t\t            \t\t\n\t\t\t            \t\t\n\t            \t\t\t\n\t            \t\t\n\t\t\t\t\t\t\t", "\n\n\t\t\t\t\t\t\t\n\t\t\t\t\t\t\t\t\n\t\t            \t\t\t\t for Sale\n\t\t            \t\t\t\n\t\t\t\t\t\t\t\t\n\t\t\t\t\t\t\t\t\n\t\t\t\t\t\t\t\t\n\t\t\t\t\t\t\t\n\n\t\t\t\t\t\t\t\n\t\t\t\t\t\t\t\t\n\t\t\t\t\t\t\t\t\n\t\t\t\t\t\t\t\t\n\t\t\t\t\t\t\t\n\t\t                \t\n\t\t                \t\t\n\t\t                \t\t\t\tin   Kondapur \n\t\t                \t\t\n\t\t\t\t\t\t           \n\t         \t\t    \t\t\n\t\t           \t\t\t\n\t\t           \t\t\t\n                   "], "bhk": "\n\t\t\t            \t\t\n\t\t\t            \t\t\t\n\t\t\t            \t\t\t\t3 BHK Flat\n\t\t\t            \t\t\t\n\t\t\t            \t\t\t\n\t\t\t            \t\t\n\t\t\t            \t\t\n\t\t\t            \t", "societyName": "Manbhum Around the Grove", "moreData": [["super area", "1980\u00a0sqft"], ["status", "\n\t\t\t\t\t\t\t\tPossession by Dec '20\n\t\t\t\t\t\t\t"], ["floor", "7 out of 10 floors"], ["transaction", "New Property"], ["furnishing", "Unfurnished"], ["car parking", "1 Covered"], ["bathroom", "3"]]},
{"price": "\u20b9 87.3 Lac", "title": ["\n\t            \t\t\n\t            \t\t\n\t            \t\t\n\t\t\t\t\t\t\t\n\t            \t\t\t\n\t            \t\t\t\n\t            \t\t\t\t\n\t\t\t            \t\t\n\t\t\t            \t\t\n\t\t\t            \t\t\n\t\t\t            \t\t\n\t            \t\t\t\n\t            \t\t\n\t\t\t\t\t\t\t", "\n\n\t\t\t\t\t\t\t\n\t\t\t\t\t\t\t\t\n\t\t            \t\t\t\t for Sale\n\t\t            \t\t\t\n\t\t\t\t\t\t\t\t\n\t\t\t\t\t\t\t\t\n\t\t\t\t\t\t\t\t\n\t\t\t\t\t\t\t\n\n\t\t\t\t\t\t\t\n\t\t\t\t\t\t\t\t\n\t\t\t\t\t\t\t\t\n\t\t\t\t\t\t\t\t\n\t\t\t\t\t\t\t\n\t\t                \t\n\t\t                \t\t\n\t\t                \t\t\t\tin   Yapral \n\t\t                \t\t\n\t\t\t\t\t\t           \n\t         \t\t    \t\t\n\t\t           \t\t\t\n\t\t           \t\t\t\n                   "], "bhk": "\n\t\t\t            \t\t\n\t\t\t            \t\t\t\n\t\t\t            \t\t\t\t3 BHK Flat\n\t\t\t            \t\t\t\n\t\t\t            \t\t\t\n\t\t\t            \t\t\n\t\t\t            \t\t\n\t\t\t            \t", "societyName": "Patels Bright View", "moreData": [["super area", "2030\u00a0sqft"], ["status", "Ready to Move"], ["floor", "3 out of 5 floors"], ["transaction", "New Property"], ["furnishing", "Semi-Furnished"], ["car parking", "1 Covered"], ["bathroom", "3"]]},
{"price": "\u20b9 85 Lac", "title": ["\n\t            \t\t\n\t            \t\t\n\t            \t\t\n\t\t\t\t\t\t\t\n\t            \t\t\t\n\t            \t\t\t\n\t            \t\t\t\t\n\t\t\t            \t\t\n\t\t\t            \t\t\n\t\t\t            \t\t\n\t\t\t            \t\t\n\t            \t\t\t\n\t            \t\t\n\t\t\t\t\t\t\t", "\n\n\t\t\t\t\t\t\t\n\t\t\t\t\t\t\t\t\n\t\t            \t\t\t\t for Sale\n\t\t            \t\t\t\n\t\t\t\t\t\t\t\t\n\t\t\t\t\t\t\t\t\n\t\t\t\t\t\t\t\t\n\t\t\t\t\t\t\t\n\n\t\t\t\t\t\t\t\n\t\t\t\t\t\t\t\t\n\t\t\t\t\t\t\t\t\n\t\t\t\t\t\t\t\t\n\t\t\t\t\t\t\t\n\t\t                \t\n\t\t                \t\t\n\t\t                \t\t\t\tin   Kukatpally, NH  9 \n\t\t                \t\t\n\t\t\t\t\t\t           \n\t         \t\t    \t\t\n\t\t           \t\t\t\n\t\t           \t\t\t\n                   "], "bhk": "\n\t\t\t            \t\t\n\t\t\t            \t\t\t\n\t\t\t            \t\t\t\t3 BHK Flat\n\t\t\t            \t\t\t\n\t\t\t            \t\t\t\n\t\t\t            \t\t\n\t\t\t            \t\t\n\t\t\t            \t", "societyName": "Ramky One Marvel", "moreData": [["super area", "1620\u00a0sqft"], ["status", "Ready to Move"], ["transaction", "New Property"], ["furnishing", "Unfurnished"], ["car parking", "1 Covered"], ["bathroom", "3"]]},
{"price": "\u20b9 67.8 Lac", "title": ["\n\t            \t\t\n\t            \t\t\n\t            \t\t\n\t\t\t\t\t\t\t\n\t            \t\t\t\n\t            \t\t\t\n\t            \t\t\t\t\n\t\t\t            \t\t\n\t\t\t            \t\t\n\t\t\t            \t\t\n\t\t\t            \t\t\n\t            \t\t\t\n\t            \t\t\n\t\t\t\t\t\t\t", "\n\n\t\t\t\t\t\t\t\n\t\t\t\t\t\t\t\t\n\t\t            \t\t\t\t for Sale\n\t\t            \t\t\t\n\t\t\t\t\t\t\t\t\n\t\t\t\t\t\t\t\t\n\t\t\t\t\t\t\t\t\n\t\t\t\t\t\t\t\n\n\t\t\t\t\t\t\t\n\t\t\t\t\t\t\t\t\n\t\t\t\t\t\t\t\t\n\t\t\t\t\t\t\t\t\n\t\t\t\t\t\t\t\n\t\t                \t\n\t\t                \t\t\n\t\t                \t\t\t\tin   Hafeezpet, NH  9 \n\t\t                \t\t\n\t\t\t\t\t\t           \n\t         \t\t    \t\t\n\t\t           \t\t\t\n\t\t           \t\t\t\n                   "], "bhk": "\n\t\t\t            \t\t\n\t\t\t            \t\t\t\n\t\t\t            \t\t\t\t2 BHK Flat\n\t\t\t            \t\t\t\n\t\t\t            \t\t\t\n\t\t\t            \t\t\n\t\t\t            \t\t\n\t\t\t            \t", "societyName": "Lake City", "moreData": [["super area", "1233\u00a0sqft"], ["status", "Ready to Move"], ["transaction", "New Property"], ["furnishing", "Unfurnished"], ["car parking", "1 Covered"], ["bathroom", "2"]]},
{"price": "\u20b9 69 Lac", "title": ["\n\t            \t\t\n\t            \t\t\n\t            \t\t\n\t\t\t\t\t\t\t\n\t            \t\t\t\n\t            \t\t\t\n\t            \t\t\t\t\n\t\t\t            \t\t\n\t\t\t            \t\t\n\t\t\t            \t\t\n\t\t\t            \t\t\n\t            \t\t\t\n\t            \t\t\n\t\t\t\t\t\t\t", "\n\n\t\t\t\t\t\t\t\n\t\t\t\t\t\t\t\t\n\t\t            \t\t\t\t for Sale\n\t\t            \t\t\t\n\t\t\t\t\t\t\t\t\n\t\t\t\t\t\t\t\t\n\t\t\t\t\t\t\t\t\n\t\t\t\t\t\t\t\n\n\t\t\t\t\t\t\t\n\t\t\t\t\t\t\t\t\n\t\t\t\t\t\t\t\t\n\t\t\t\t\t\t\t\t\n\t\t\t\t\t\t\t\n\t\t                \t\n\t\t                \t\t\n\t\t                \t\t\t\tin   Sanath Nagar, NH  9 \n\t\t                \t\t\n\t\t\t\t\t\t           \n\t         \t\t    \t\t\n\t\t           \t\t\t\n\t\t           \t\t\t\n                   "], "bhk": "\n\t\t\t            \t\t\n\t\t\t            \t\t\t\n\t\t\t            \t\t\t\t2 BHK Flat\n\t\t\t            \t\t\t\n\t\t\t            \t\t\t\n\t\t\t            \t\t\n\t\t\t            \t\t\n\t\t\t            \t", "societyName": "Civitas", "moreData": [["super area", "1211\u00a0sqft"], ["status", "\n\t\t\t\t\t\t\t\tPossession by Jul '20\n\t\t\t\t\t\t\t"], ["floor", "3 out of 5 floors"], ["transaction", "New Property"], ["furnishing", "Unfurnished"], ["car parking", "1 Covered"], ["bathroom", "3"]]},
{"price": "\u20b9 58.4 Lac", "title": ["\n\t            \t\t\n\t            \t\t\n\t            \t\t\n\t\t\t\t\t\t\t\n\t            \t\t\t\n\t            \t\t\t\n\t            \t\t\t\t\n\t\t\t            \t\t\n\t\t\t            \t\t\n\t\t\t            \t\t\n\t\t\t            \t\t\n\t            \t\t\t\n\t            \t\t\n\t\t\t\t\t\t\t", "\n\n\t\t\t\t\t\t\t\n\t\t\t\t\t\t\t\t\n\t\t            \t\t\t\t for Sale\n\t\t            \t\t\t\n\t\t\t\t\t\t\t\t\n\t\t\t\t\t\t\t\t\n\t\t\t\t\t\t\t\t\n\t\t\t\t\t\t\t\n\n\t\t\t\t\t\t\t\n\t\t\t\t\t\t\t\t\n\t\t\t\t\t\t\t\t\n\t\t\t\t\t\t\t\t\n\t\t\t\t\t\t\t\n\t\t                \t\n\t\t                \t\t\n\t\t                \t\t\t\tin   Adibatla \n\t\t                \t\t\n\t\t\t\t\t\t           \n\t         \t\t    \t\t\n\t\t           \t\t\t\n\t\t           \t\t\t\n                   "], "bhk": "\n\t\t\t            \t\t\n\t\t\t            \t\t\t\n\t\t\t            \t\t\t\t3 BHK Flat\n\t\t\t            \t\t\t\n\t\t\t            \t\t\t\n\t\t\t            \t\t\n\t\t\t            \t\t\n\t\t\t            \t", "societyName": "Rochishmati Noveo Homes", "moreData": [["super area", "1580\u00a0sqft"], ["status", "\n\t\t\t\t\t\t\t\tPossession by Jun '20\n\t\t\t\t\t\t\t"], ["floor", "1"], ["transaction", "New Property"], ["furnishing", "Unfurnished"], ["car parking", "1 Covered"], ["bathroom", "3"]]},
{"price": "\u20b9 78.8 Lac", "title": ["\n\t            \t\t\n\t            \t\t\n\t            \t\t\n\t\t\t\t\t\t\t\n\t            \t\t\t\n\t            \t\t\t\n\t            \t\t\t\t\n\t\t\t            \t\t\n\t\t\t            \t\t\n\t\t\t            \t\t\n\t\t\t            \t\t\n\t            \t\t\t\n\t            \t\t\n\t\t\t\t\t\t\t", "\n\n\t\t\t\t\t\t\t\n\t\t\t\t\t\t\t\t\n\t\t            \t\t\t\t for Sale\n\t\t            \t\t\t\n\t\t\t\t\t\t\t\t\n\t\t\t\t\t\t\t\t\n\t\t\t\t\t\t\t\t\n\t\t\t\t\t\t\t\n\n\t\t\t\t\t\t\t\n\t\t\t\t\t\t\t\t\n\t\t\t\t\t\t\t\t\n\t\t\t\t\t\t\t\t\n\t\t\t\t\t\t\t\n\t\t                \t\n\t\t                \t\t\n\t\t                \t\t\t\tin   Alkapur Township, Manikonda, Outer Ring Road \n\t\t                \t\t\n\t\t\t\t\t\t           \n\t         \t\t    \t\t\n\t\t           \t\t\t\n\t\t           \t\t\t\n                   "], "bhk": "\n\t\t\t            \t\t\n\t\t\t            \t\t\t\n\t\t\t            \t\t\t\t3 BHK Flat\n\t\t\t            \t\t\t\n\t\t\t            \t\t\t\n\t\t\t            \t\t\n\t\t\t            \t\t\n\t\t\t            \t", "societyName": "Village Pointe", "moreData": [["super area", "1676\u00a0sqft"], ["status", "\n\t\t\t\t\t\t\t\tPossession by Dec '20\n\t\t\t\t\t\t\t"], ["transaction", "New Property"], ["furnishing", "Unfurnished"], ["car parking", "1 Covered"], ["bathroom", "3"]]},
{"price": "\u20b9 45.6 Lac", "title": ["\n\t            \t\t\n\t            \t\t\n\t            \t\t\n\t\t\t\t\t\t\t\n\t            \t\t\t\n\t            \t\t\t\n\t            \t\t\t\t\n\t\t\t            \t\t\n\t\t\t            \t\t\n\t\t\t            \t\t\n\t\t\t            \t\t\n\t            \t\t\t\n\t            \t\t\n\t\t\t\t\t\t\t", "\n\n\t\t\t\t\t\t\t\n\t\t\t\t\t\t\t\t\n\t\t            \t\t\t\t for Sale\n\t\t            \t\t\t\n\t\t\t\t\t\t\t\t\n\t\t\t\t\t\t\t\t\n\t\t\t\t\t\t\t\t\n\t\t\t\t\t\t\t\n\n\t\t\t\t\t\t\t\n\t\t\t\t\t\t\t\t\n\t\t\t\t\t\t\t\t\n\t\t\t\t\t\t\t\t\n\t\t\t\t\t\t\t\n\t\t                \t\n\t\t                \t\t\n\t\t                \t\t\t\tin   Pocharam, NH 2 2 \n\t\t                \t\t\n\t\t\t\t\t\t           \n\t         \t\t    \t\t\n\t\t           \t\t\t\n\t\t           \t\t\t\n                   "], "bhk": "\n\t\t\t            \t\t\n\t\t\t            \t\t\t\n\t\t\t            \t\t\t\t3 BHK Flat\n\t\t\t            \t\t\t\n\t\t\t            \t\t\t\n\t\t\t            \t\t\n\t\t\t            \t\t\n\t\t\t            \t", "societyName": "Modi Emerald Heights", "moreData": [["super area", "1360\u00a0sqft"], ["status", "Ready to Move"], ["floor", "1 out of 7 floors"], ["transaction", "New Property"], ["furnishing", "Unfurnished"], ["car parking", "1 Covered"], ["bathroom", "3"]]},
{"price": "\u20b9 75.9 Lac", "title": ["\n\t            \t\t\n\t            \t\t\n\t            \t\t\n\t\t\t\t\t\t\t\n\t            \t\t\t\n\t            \t\t\t\n\t            \t\t\t\t\n\t\t\t            \t\t\n\t\t\t            \t\t\n\t\t\t            \t\t\n\t\t\t            \t\t\n\t            \t\t\t\n\t            \t\t\n\t\t\t\t\t\t\t", "\n\n\t\t\t\t\t\t\t\n\t\t\t\t\t\t\t\t\n\t\t            \t\t\t\t for Sale\n\t\t            \t\t\t\n\t\t\t\t\t\t\t\t\n\t\t\t\t\t\t\t\t\n\t\t\t\t\t\t\t\t\n\t\t\t\t\t\t\t\n\n\t\t\t\t\t\t\t\n\t\t\t\t\t\t\t\t\n\t\t\t\t\t\t\t\t\n\t\t\t\t\t\t\t\t\n\t\t\t\t\t\t\t\n\t\t                \t\n\t\t                \t\t\n\t\t                \t\t\t\tin   Nagole \n\t\t                \t\t\n\t\t\t\t\t\t           \n\t         \t\t    \t\t\n\t\t           \t\t\t\n\t\t           \t\t\t\n                   "], "bhk": "\n\t\t\t            \t\t\n\t\t\t            \t\t\t\n\t\t\t            \t\t\t\t3 BHK Flat\n\t\t\t            \t\t\t\n\t\t\t            \t\t\t\n\t\t\t            \t\t\n\t\t\t            \t\t\n\t\t\t            \t", "societyName": "Land Mark", "moreData": [["super area", "1650\u00a0sqft"], ["status", "\n\t\t\t\t\t\t\t\tPossession by Mar '20\n\t\t\t\t\t\t\t"], ["transaction", "New Property"], ["furnishing", "Unfurnished"], ["bathroom", "3"]]},
{"price": "\u20b9 70 Lac", "title": ["\n\t            \t\t\n\t            \t\t\n\t            \t\t\n\t\t\t\t\t\t\t\n\t            \t\t\t\n\t            \t\t\t\n\t            \t\t\t\t\n\t\t\t            \t\t\n\t\t\t            \t\t\n\t\t\t            \t\t\n\t\t\t            \t\t\n\t            \t\t\t\n\t            \t\t\n\t\t\t\t\t\t\t", "\n\n\t\t\t\t\t\t\t\n\t\t\t\t\t\t\t\t\n\t\t            \t\t\t\t for Sale\n\t\t            \t\t\t\n\t\t\t\t\t\t\t\t\n\t\t\t\t\t\t\t\t\n\t\t\t\t\t\t\t\t\n\t\t\t\t\t\t\t\n\n\t\t\t\t\t\t\t\n\t\t\t\t\t\t\t\t\n\t\t\t\t\t\t\t\t\n\t\t\t\t\t\t\t\t\n\t\t\t\t\t\t\t\n\t\t                \t\n\t\t                \t\t\n\t\t                \t\t\t\tin   Manikonda, Outer Ring Road \n\t\t                \t\t\n\t\t\t\t\t\t           \n\t         \t\t    \t\t\n\t\t           \t\t\t\n\t\t           \t\t\t\n                   "], "bhk": "\n\t\t\t            \t\t\n\t\t\t            \t\t\t\n\t\t\t            \t\t\t\t2 BHK Flat\n\t\t\t            \t\t\t\n\t\t\t            \t\t\t\n\t\t\t            \t\t\n\t\t\t            \t\t\n\t\t\t            \t", "societyName": "Vihhari", "moreData": [["super area", "1320\u00a0sqft"], ["status", "Ready to Move"], ["floor", "5 out of 10 floors"], ["transaction", "New Property"], ["furnishing", "Unfurnished"], ["car parking", "1 Covered"], ["bathroom", "2"]]},
{"price": "\u20b9 61.1 Lac", "title": ["\n\t            \t\t\n\t            \t\t\n\t            \t\t\n\t\t\t\t\t\t\t\n\t            \t\t\t\n\t            \t\t\t\n\t            \t\t\t\t\n\t\t\t            \t\t\n\t\t\t            \t\t\n\t\t\t            \t\t\n\t\t\t            \t\t\n\t            \t\t\t\n\t            \t\t\n\t\t\t\t\t\t\t", "\n\n\t\t\t\t\t\t\t\n\t\t\t\t\t\t\t\t\n\t\t            \t\t\t\t for Sale\n\t\t            \t\t\t\n\t\t\t\t\t\t\t\t\n\t\t\t\t\t\t\t\t\n\t\t\t\t\t\t\t\t\n\t\t\t\t\t\t\t\n\n\t\t\t\t\t\t\t\n\t\t\t\t\t\t\t\t\n\t\t\t\t\t\t\t\t\n\t\t\t\t\t\t\t\t\n\t\t\t\t\t\t\t\n\t\t                \t\n\t\t                \t\t\n\t\t                \t\t\t\tin   Puppalaguda \n\t\t                \t\t\n\t\t\t\t\t\t           \n\t         \t\t    \t\t\n\t\t           \t\t\t\n\t\t           \t\t\t\n                   "], "bhk": "\n\t\t\t            \t\t\n\t\t\t            \t\t\t\n\t\t\t            \t\t\t\t2 BHK Flat\n\t\t\t            \t\t\t\n\t\t\t            \t\t\t\n\t\t\t            \t\t\n\t\t\t            \t\t\n\t\t\t            \t", "societyName": "Golden Oriole", "moreData": [["super area", "1272\u00a0sqft"], ["status", "\n\t\t\t\t\t\t\t\tPossession by Dec '20\n\t\t\t\t\t\t\t"], ["transaction", "New Property"], ["furnishing", "Unfurnished"], ["car parking", "1 Covered"], ["bathroom", "2"]]},
{"price": "\u20b9 67.7 Lac", "title": ["\n\t            \t\t\n\t            \t\t\n\t            \t\t\n\t\t\t\t\t\t\t\n\t            \t\t\t\n\t            \t\t\t\n\t            \t\t\t\t\n\t\t\t            \t\t\n\t\t\t            \t\t\n\t\t\t            \t\t\n\t\t\t            \t\t\n\t            \t\t\t\n\t            \t\t\n\t\t\t\t\t\t\t", "\n\n\t\t\t\t\t\t\t\n\t\t\t\t\t\t\t\t\n\t\t            \t\t\t\t for Sale\n\t\t            \t\t\t\n\t\t\t\t\t\t\t\t\n\t\t\t\t\t\t\t\t\n\t\t\t\t\t\t\t\t\n\t\t\t\t\t\t\t\n\n\t\t\t\t\t\t\t\n\t\t\t\t\t\t\t\t\n\t\t\t\t\t\t\t\t\n\t\t\t\t\t\t\t\t\n\t\t\t\t\t\t\t\n\t\t                \t\n\t\t                \t\t\n\t\t                \t\t\t\tin   Bachupally, Outer Ring Road \n\t\t                \t\t\n\t\t\t\t\t\t           \n\t         \t\t    \t\t\n\t\t           \t\t\t\n\t\t           \t\t\t\n                   "], "bhk": "\n\t\t\t            \t\t\n\t\t\t            \t\t\t\n\t\t\t            \t\t\t\t3 BHK Flat\n\t\t\t            \t\t\t\n\t\t\t            \t\t\t\n\t\t\t            \t\t\n\t\t\t            \t\t\n\t\t\t            \t", "societyName": "Vishnu Krupas Golden Oriole", "moreData": [["super area", "1540\u00a0sqft"], ["status", "\n\t\t\t\t\t\t\t\tPossession by Dec '20\n\t\t\t\t\t\t\t"], ["floor", "6 out of 6 floors"], ["transaction", "New Property"], ["furnishing", "Unfurnished"], ["bathroom", "3"]]},
{"price": "\u20b9 56.3 Lac", "title": ["\n\t            \t\t\n\t            \t\t\n\t            \t\t\n\t\t\t\t\t\t\t\n\t            \t\t\t\n\t            \t\t\t\n\t            \t\t\t\t\n\t\t\t            \t\t\n\t\t\t            \t\t\n\t\t\t            \t\t\n\t\t\t            \t\t\n\t            \t\t\t\n\t            \t\t\n\t\t\t\t\t\t\t", "\n\n\t\t\t\t\t\t\t\n\t\t\t\t\t\t\t\t\n\t\t            \t\t\t\t for Sale\n\t\t            \t\t\t\n\t\t\t\t\t\t\t\t\n\t\t\t\t\t\t\t\t\n\t\t\t\t\t\t\t\t\n\t\t\t\t\t\t\t\n\n\t\t\t\t\t\t\t\n\t\t\t\t\t\t\t\t\n\t\t\t\t\t\t\t\t\n\t\t\t\t\t\t\t\t\n\t\t\t\t\t\t\t\n\t\t                \t\n\t\t                \t\t\n\t\t                \t\t\t\tin   Balanagar \n\t\t                \t\t\n\t\t\t\t\t\t           \n\t         \t\t    \t\t\n\t\t           \t\t\t\n\t\t           \t\t\t\n                   "], "bhk": "\n\t\t\t            \t\t\n\t\t\t            \t\t\t\n\t\t\t            \t\t\t\t2 BHK Flat\n\t\t\t            \t\t\t\n\t\t\t            \t\t\t\n\t\t\t            \t\t\n\t\t\t            \t\t\n\t\t\t            \t", "societyName": "Ridge Towers", "moreData": [["super area", "1295\u00a0sqft"], ["status", "\n\t\t\t\t\t\t\t\tPossession by Mar '21\n\t\t\t\t\t\t\t"], ["floor", "9"], ["transaction", "New Property"], ["furnishing", "Unfurnished"], ["car parking", "1 Covered"], ["bathroom", "2"]]},
{"price": "\u20b9 1.09 Cr", "title": ["\n\t            \t\t\n\t            \t\t\n\t            \t\t\n\t\t\t\t\t\t\t\n\t            \t\t\t\n\t            \t\t\t\n\t            \t\t\t\t\n\t\t\t            \t\t\n\t\t\t            \t\t\n\t\t\t            \t\t\n\t\t\t            \t\t\n\t            \t\t\t\n\t            \t\t\n\t\t\t\t\t\t\t", "\n\n\t\t\t\t\t\t\t\n\t\t\t\t\t\t\t\t\n\t\t            \t\t\t\t for Sale\n\t\t            \t\t\t\n\t\t\t\t\t\t\t\t\n\t\t\t\t\t\t\t\t\n\t\t\t\t\t\t\t\t\n\t\t\t\t\t\t\t\n\n\t\t\t\t\t\t\t\n\t\t\t\t\t\t\t\t\n\t\t\t\t\t\t\t\t\n\t\t\t\t\t\t\t\t\n\t\t\t\t\t\t\t\n\t\t                \t\n\t\t                \t\t\n\t\t                \t\t\t\tin   Nanakram Guda \n\t\t                \t\t\n\t\t\t\t\t\t           \n\t         \t\t    \t\t\n\t\t           \t\t\t\n\t\t           \t\t\t\n                   "], "bhk": "\n\t\t\t            \t\t\n\t\t\t            \t\t\t\n\t\t\t            \t\t\t\t3 BHK Flat\n\t\t\t            \t\t\t\n\t\t\t            \t\t\t\n\t\t\t            \t\t\n\t\t\t            \t\t\n\t\t\t            \t", "societyName": "Vasavi GP Trend", "moreData": [["super area", "1820\u00a0sqft"], ["status", "\n\t\t\t\t\t\t\t\tPossession by Mar '20\n\t\t\t\t\t\t\t"], ["transaction", "New Property"], ["furnishing", "Unfurnished"], ["bathroom", "2"]]},
{"price": "\u20b9 98.6 Lac", "title": ["\n\t            \t\t\n\t            \t\t\n\t            \t\t\n\t\t\t\t\t\t\t\n\t            \t\t\t\n\t            \t\t\t\n\t            \t\t\t\t\n\t\t\t            \t\t\n\t\t\t            \t\t\n\t\t\t            \t\t\n\t\t\t            \t\t\n\t            \t\t\t\n\t            \t\t\n\t\t\t\t\t\t\t", "\n\n\t\t\t\t\t\t\t\n\t\t\t\t\t\t\t\t\n\t\t            \t\t\t\t for Sale\n\t\t            \t\t\t\n\t\t\t\t\t\t\t\t\n\t\t\t\t\t\t\t\t\n\t\t\t\t\t\t\t\t\n\t\t\t\t\t\t\t\n\n\t\t\t\t\t\t\t\n\t\t\t\t\t\t\t\t\n\t\t\t\t\t\t\t\t\n\t\t\t\t\t\t\t\t\n\t\t\t\t\t\t\t\n\t\t                \t\n\t\t                \t\t\n\t\t                \t\t\t\tin   Pragathi Nagar, Kukatpally \n\t\t                \t\t\n\t\t\t\t\t\t           \n\t         \t\t    \t\t\n\t\t           \t\t\t\n\t\t           \t\t\t\n                   "], "bhk": "\n\t\t\t            \t\t\n\t\t\t            \t\t\t\n\t\t\t            \t\t\t\t3 BHK Flat\n\t\t\t            \t\t\t\n\t\t\t            \t\t\t\n\t\t\t            \t\t\n\t\t\t            \t\t\n\t\t\t            \t", "societyName": "My Space", "moreData": [["super area", "2375\u00a0sqft"], ["status", "\n\t\t\t\t\t\t\t\tPossession by Dec '20\n\t\t\t\t\t\t\t"], ["transaction", "New Property"], ["furnishing", "Unfurnished"], ["car parking", "1 Covered"], ["bathroom", "3"]]},
{"price": "\u20b9 6.25 Cr", "title": ["\n\t            \t\t\n\t            \t\t\n\t            \t\t\n\t\t\t\t\t\t\t\n\t            \t\t\t\n\t            \t\t\t\n\t            \t\t\t\t\n\t\t\t            \t\t\n\t\t\t            \t\t\n\t\t\t            \t\t\n\t\t\t            \t\t\n\t            \t\t\t\n\t            \t\t\n\t\t\t\t\t\t\t", "\n\n\t\t\t\t\t\t\t\n\t\t\t\t\t\t\t\t\n\t\t            \t\t\t\t for Sale\n\t\t            \t\t\t\n\t\t\t\t\t\t\t\t\n\t\t\t\t\t\t\t\t\n\t\t\t\t\t\t\t\t\n\t\t\t\t\t\t\t\n\n\t\t\t\t\t\t\t\n\t\t\t\t\t\t\t\t\n\t\t\t\t\t\t\t\t\n\t\t\t\t\t\t\t\t\n\t\t\t\t\t\t\t\n\t\t                \t\n\t\t                \t\t\n\t\t                \t\t\t\tin   Shaikpet \n\t\t                \t\t\n\t\t\t\t\t\t           \n\t         \t\t    \t\t\n\t\t           \t\t\t\n\t\t           \t\t\t\n                   "], "bhk": "\n\t\t\t            \t\t\n\t\t\t            \t\t\t\n\t\t\t            \t\t\t\t4 BHK Flat\n\t\t\t            \t\t\t\n\t\t\t            \t\t\t\n\t\t\t            \t\t\n\t\t\t            \t\t\n\t\t\t            \t", "societyName": "Aparna One", "moreData": [["super area", "5216\u00a0sqft"], ["status", "\n\t\t\t\t\t\t\t\tPossession by Dec '22\n\t\t\t\t\t\t\t"], ["transaction", "New Property"], ["furnishing", "Unfurnished"], ["car parking", "1 Covered"], ["bathroom", "4"]]},
{"price": "\u20b9 74.4 Lac", "title": ["\n\t            \t\t\n\t            \t\t\n\t            \t\t\n\t\t\t\t\t\t\t\n\t            \t\t\t\n\t            \t\t\t\n\t            \t\t\t\t\n\t\t\t            \t\t\n\t\t\t            \t\t\n\t\t\t            \t\t\n\t\t\t            \t\t\n\t            \t\t\t\n\t            \t\t\n\t\t\t\t\t\t\t", "\n\n\t\t\t\t\t\t\t\n\t\t\t\t\t\t\t\t\n\t\t            \t\t\t\t for Sale\n\t\t            \t\t\t\n\t\t\t\t\t\t\t\t\n\t\t\t\t\t\t\t\t\n\t\t\t\t\t\t\t\t\n\t\t\t\t\t\t\t\n\n\t\t\t\t\t\t\t\n\t\t\t\t\t\t\t\t\n\t\t\t\t\t\t\t\t\n\t\t\t\t\t\t\t\t\n\t\t\t\t\t\t\t\n\t\t                \t\n\t\t                \t\t\n\t\t                \t\t\t\tin   Madinaguda, Hafeezpet, NH  9 \n\t\t                \t\t\n\t\t\t\t\t\t           \n\t         \t\t    \t\t\n\t\t           \t\t\t\n\t\t           \t\t\t\n                   "], "bhk": "\n\t\t\t            \t\t\n\t\t\t            \t\t\t\n\t\t\t            \t\t\t\t2 BHK Flat\n\t\t\t            \t\t\t\n\t\t\t            \t\t\t\n\t\t\t            \t\t\n\t\t\t            \t\t\n\t\t\t            \t", "societyName": "Concrete Vivanta", "moreData": [["super area", "1305\u00a0sqft"], ["status", "Ready to Move"], ["transaction", "New Property"], ["furnishing", "Unfurnished"], ["bathroom", "2"]]},
{"price": "\u20b9 55.4 Lac", "title": ["\n\t            \t\t\n\t            \t\t\n\t            \t\t\n\t\t\t\t\t\t\t\n\t            \t\t\t\n\t            \t\t\t\n\t            \t\t\t\t\n\t\t\t            \t\t\n\t\t\t            \t\t\n\t\t\t            \t\t\n\t\t\t            \t\t\n\t            \t\t\t\n\t            \t\t\n\t\t\t\t\t\t\t", "\n\n\t\t\t\t\t\t\t\n\t\t\t\t\t\t\t\t\n\t\t            \t\t\t\t for Sale\n\t\t            \t\t\t\n\t\t\t\t\t\t\t\t\n\t\t\t\t\t\t\t\t\n\t\t\t\t\t\t\t\t\n\t\t\t\t\t\t\t\n\n\t\t\t\t\t\t\t\n\t\t\t\t\t\t\t\t\n\t\t\t\t\t\t\t\t\n\t\t\t\t\t\t\t\t\n\t\t\t\t\t\t\t\n\t\t                \t\n\t\t                \t\t\n\t\t                \t\t\t\tin   Saroornagar, NH  9 \n\t\t                \t\t\n\t\t\t\t\t\t           \n\t         \t\t    \t\t\n\t\t           \t\t\t\n\t\t           \t\t\t\n                   "], "bhk": "\n\t\t\t            \t\t\n\t\t\t            \t\t\t\n\t\t\t            \t\t\t\t2 BHK Flat\n\t\t\t            \t\t\t\n\t\t\t            \t\t\t\n\t\t\t            \t\t\n\t\t\t            \t\t\n\t\t\t            \t", "societyName": "Flemingo", "moreData": [["super area", "1155\u00a0sqft"], ["status", "\n\t\t\t\t\t\t\t\tPossession by Mar '20\n\t\t\t\t\t\t\t"], ["transaction", "New Property"], ["furnishing", "Unfurnished"], ["car parking", "1 Covered"], ["bathroom", "2"]]},
{"price": "\u20b9 1.05 Cr", "title": ["\n\t            \t\t\n\t            \t\t\n\t            \t\t\n\t\t\t\t\t\t\t\n\t            \t\t\t\n\t            \t\t\t\n\t            \t\t\t\t\n\t\t\t            \t\t\n\t\t\t            \t\t\n\t\t\t            \t\t\n\t\t\t            \t\t\n\t            \t\t\t\n\t            \t\t\n\t\t\t\t\t\t\t", "\n\n\t\t\t\t\t\t\t\n\t\t\t\t\t\t\t\t\n\t\t            \t\t\t\t for Sale\n\t\t            \t\t\t\n\t\t\t\t\t\t\t\t\n\t\t\t\t\t\t\t\t\n\t\t\t\t\t\t\t\t\n\t\t\t\t\t\t\t\n\n\t\t\t\t\t\t\t\n\t\t\t\t\t\t\t\t\n\t\t\t\t\t\t\t\t\n\t\t\t\t\t\t\t\t\n\t\t\t\t\t\t\t\n\t\t                \t\n\t\t                \t\t\n\t\t                \t\t\t\tin   Manchirevula, Outer Ring Road \n\t\t                \t\t\n\t\t\t\t\t\t           \n\t         \t\t    \t\t\n\t\t           \t\t\t\n\t\t           \t\t\t\n                   "], "bhk": "\n\t\t\t            \t\t\n\t\t\t            \t\t\t\n\t\t\t            \t\t\t\t3 BHK Flat\n\t\t\t            \t\t\t\n\t\t\t            \t\t\t\n\t\t\t            \t\t\n\t\t\t            \t\t\n\t\t\t            \t", "societyName": "EIPL Rivera", "moreData": [["super area", "2025\u00a0sqft"], ["status", "\n\t\t\t\t\t\t\t\tPossession by Dec '19\n\t\t\t\t\t\t\t"], ["floor", "6 out of 6 floors"], ["transaction", "New Property"], ["furnishing", "Unfurnished"], ["car parking", "1 Covered"], ["bathroom", "3"]]},
{"price": "\u20b9 81.2 Lac", "title": ["\n\t            \t\t\n\t            \t\t\n\t            \t\t\n\t\t\t\t\t\t\t\n\t            \t\t\t\n\t            \t\t\t\n\t            \t\t\t\t\n\t\t\t            \t\t\n\t\t\t            \t\t\n\t\t\t            \t\t\n\t\t\t            \t\t\n\t            \t\t\t\n\t            \t\t\n\t\t\t\t\t\t\t", "\n\n\t\t\t\t\t\t\t\n\t\t\t\t\t\t\t\t\n\t\t            \t\t\t\t for Sale\n\t\t            \t\t\t\n\t\t\t\t\t\t\t\t\n\t\t\t\t\t\t\t\t\n\t\t\t\t\t\t\t\t\n\t\t\t\t\t\t\t\n\n\t\t\t\t\t\t\t\n\t\t\t\t\t\t\t\t\n\t\t\t\t\t\t\t\t\n\t\t\t\t\t\t\t\t\n\t\t\t\t\t\t\t\n\t\t                \t\n\t\t                \t\t\n\t\t                \t\t\t\tin   Narsingi, Outer Ring Road \n\t\t                \t\t\n\t\t\t\t\t\t           \n\t         \t\t    \t\t\n\t\t           \t\t\t\n\t\t           \t\t\t\n                   "], "bhk": "\n\t\t\t            \t\t\n\t\t\t            \t\t\t\n\t\t\t            \t\t\t\t3 BHK Flat\n\t\t\t            \t\t\t\n\t\t\t            \t\t\t\n\t\t\t            \t\t\n\t\t\t            \t\t\n\t\t\t            \t", "societyName": "Riddhis Saphire", "moreData": [["super area", "1625\u00a0sqft"], ["status", "\n\t\t\t\t\t\t\t\tPossession by Jun '20\n\t\t\t\t\t\t\t"], ["transaction", "New Property"], ["furnishing", "Unfurnished"], ["bathroom", "3"]]},
{"price": "\u20b9 1.78 Cr", "title": ["\n\t            \t\t\n\t            \t\t\n\t            \t\t\n\t\t\t\t\t\t\t\n\t            \t\t\t\n\t            \t\t\t\n\t            \t\t\t\t\n\t\t\t            \t\t\n\t\t\t            \t\t\n\t\t\t            \t\t\n\t\t\t            \t\t\n\t            \t\t\t\n\t            \t\t\n\t\t\t\t\t\t\t", "\n\n\t\t\t\t\t\t\t\n\t\t\t\t\t\t\t\t\n\t\t            \t\t\t\t for Sale\n\t\t            \t\t\t\n\t\t\t\t\t\t\t\t\n\t\t\t\t\t\t\t\t\n\t\t\t\t\t\t\t\t\n\t\t\t\t\t\t\t\n\n\t\t\t\t\t\t\t\n\t\t\t\t\t\t\t\t\n\t\t\t\t\t\t\t\t\n\t\t\t\t\t\t\t\t\n\t\t\t\t\t\t\t\n\t\t                \t\n\t\t                \t\t\n\t\t                \t\t\t\tin   Miyapur, NH  9 \n\t\t                \t\t\n\t\t\t\t\t\t           \n\t         \t\t    \t\t\n\t\t           \t\t\t\n\t\t           \t\t\t\n                   "], "bhk": "\n\t\t\t            \t\t\n\t\t\t            \t\t\t\n\t\t\t            \t\t\t\t3 BHK Flat\n\t\t\t            \t\t\t\n\t\t\t            \t\t\t\n\t\t\t            \t\t\n\t\t\t            \t\t\n\t\t\t            \t", "societyName": "Dhivya Shree Shakthi", "moreData": [["super area", "3152\u00a0sqft"], ["status", "Ready to Move"], ["floor", "6 out of 9 floors"], ["transaction", "New Property"], ["furnishing", "Semi-Furnished"], ["car parking", "1 Covered"], ["bathroom", "3"]]},
{"price": "\u20b9 71 Lac", "title": ["\n\t            \t\t\n\t            \t\t\n\t            \t\t\n\t\t\t\t\t\t\t\n\t            \t\t\t\n\t            \t\t\t\n\t            \t\t\t\t\n\t\t\t            \t\t\n\t\t\t            \t\t\n\t\t\t            \t\t\n\t\t\t            \t\t\n\t            \t\t\t\n\t            \t\t\n\t\t\t\t\t\t\t", "\n\n\t\t\t\t\t\t\t\n\t\t\t\t\t\t\t\t\n\t\t            \t\t\t\t for Sale\n\t\t            \t\t\t\n\t\t\t\t\t\t\t\t\n\t\t\t\t\t\t\t\t\n\t\t\t\t\t\t\t\t\n\t\t\t\t\t\t\t\n\n\t\t\t\t\t\t\t\n\t\t\t\t\t\t\t\t\n\t\t\t\t\t\t\t\t\n\t\t\t\t\t\t\t\t\n\t\t\t\t\t\t\t\n\t\t                \t\n\t\t                \t\t\n\t\t                \t\t\t\tin   Kompally \n\t\t                \t\t\n\t\t\t\t\t\t           \n\t         \t\t    \t\t\n\t\t           \t\t\t\n\t\t           \t\t\t\n                   "], "bhk": "\n\t\t\t            \t\t\n\t\t\t            \t\t\t\n\t\t\t            \t\t\t\t3 BHK Flat\n\t\t\t            \t\t\t\n\t\t\t            \t\t\t\n\t\t\t            \t\t\n\t\t\t            \t\t\n\t\t\t            \t", "societyName": "Saket Pranamam", "moreData": [["super area", "1725\u00a0sqft"], ["status", "\n\t\t\t\t\t\t\t\tPossession by Dec '20\n\t\t\t\t\t\t\t"], ["floor", "8 out of 10 floors"], ["transaction", "New Property"], ["furnishing", "Unfurnished"], ["car parking", "1 Covered"], ["bathroom", "3"]]},
{"price": "\u20b9 1.11 Cr", "title": ["\n\t            \t\t\n\t            \t\t\n\t            \t\t\n\t\t\t\t\t\t\t\n\t            \t\t\t\n\t            \t\t\t\n\t            \t\t\t\t\n\t\t\t            \t\t\n\t\t\t            \t\t\n\t\t\t            \t\t\n\t\t\t            \t\t\n\t            \t\t\t\n\t            \t\t\n\t\t\t\t\t\t\t", "\n\n\t\t\t\t\t\t\t\n\t\t\t\t\t\t\t\t\n\t\t            \t\t\t\t for Sale\n\t\t            \t\t\t\n\t\t\t\t\t\t\t\t\n\t\t\t\t\t\t\t\t\n\t\t\t\t\t\t\t\t\n\t\t\t\t\t\t\t\n\n\t\t\t\t\t\t\t\n\t\t\t\t\t\t\t\t\n\t\t\t\t\t\t\t\t\n\t\t\t\t\t\t\t\t\n\t\t\t\t\t\t\t\n\t\t                \t\n\t\t                \t\t\n\t\t                \t\t\t\tin   Narsingi, Outer Ring Road \n\t\t                \t\t\n\t\t\t\t\t\t           \n\t         \t\t    \t\t\n\t\t           \t\t\t\n\t\t           \t\t\t\n                   "], "bhk": "\n\t\t\t            \t\t\n\t\t\t            \t\t\t\n\t\t\t            \t\t\t\t3 BHK Flat\n\t\t\t            \t\t\t\n\t\t\t            \t\t\t\n\t\t\t            \t\t\n\t\t\t            \t\t\n\t\t\t            \t", "societyName": "Hallmark Vicinia", "moreData": [["super area", "2036\u00a0sqft"], ["transaction", "New Property"], ["furnishing", "Unfurnished"], ["bathroom", "3"]]},
{"price": "\u20b9 1.65 Cr", "title": ["\n\t            \t\t\n\t            \t\t\n\t            \t\t\n\t\t\t\t\t\t\t\n\t            \t\t\t\n\t            \t\t\t\n\t            \t\t\t\t\n\t\t\t            \t\t\n\t\t\t            \t\t\n\t\t\t            \t\t\n\t\t\t            \t\t\n\t            \t\t\t\n\t            \t\t\n\t\t\t\t\t\t\t", "\n\n\t\t\t\t\t\t\t\n\t\t\t\t\t\t\t\t\n\t\t            \t\t\t\t for Sale\n\t\t            \t\t\t\n\t\t\t\t\t\t\t\t\n\t\t\t\t\t\t\t\t\n\t\t\t\t\t\t\t\t\n\t\t\t\t\t\t\t\n\n\t\t\t\t\t\t\t\n\t\t\t\t\t\t\t\t\n\t\t\t\t\t\t\t\t\n\t\t\t\t\t\t\t\t\n\t\t\t\t\t\t\t\n\t\t                \t\n\t\t                \t\t\n\t\t                \t\t\t\tin   Narsingi, Outer Ring Road \n\t\t                \t\t\n\t\t\t\t\t\t           \n\t         \t\t    \t\t\n\t\t           \t\t\t\n\t\t           \t\t\t\n                   "], "bhk": "\n\t\t\t            \t\t\n\t\t\t            \t\t\t\n\t\t\t            \t\t\t\t3 BHK Flat\n\t\t\t            \t\t\t\n\t\t\t            \t\t\t\n\t\t\t            \t\t\n\t\t\t            \t\t\n\t\t\t            \t", "societyName": "Jayabheri The Summit", "moreData": [["super area", "2125\u00a0sqft"], ["status", "\n\t\t\t\t\t\t\t\tPossession by Dec '20\n\t\t\t\t\t\t\t"], ["floor", "22 out of 30 floors"], ["transaction", "New Property"], ["furnishing", "Unfurnished"], ["bathroom", "3"]]},
{"price": "\u20b9 1.60 Cr", "title": ["\n\t            \t\t\n\t            \t\t\n\t            \t\t\n\t\t\t\t\t\t\t\n\t            \t\t\t\n\t            \t\t\t\n\t            \t\t\t\t\n\t\t\t            \t\t\n\t\t\t            \t\t\n\t\t\t            \t\t\n\t\t\t            \t\t\n\t            \t\t\t\n\t            \t\t\n\t\t\t\t\t\t\t", "\n\n\t\t\t\t\t\t\t\n\t\t\t\t\t\t\t\t\n\t\t            \t\t\t\t for Sale\n\t\t            \t\t\t\n\t\t\t\t\t\t\t\t\n\t\t\t\t\t\t\t\t\n\t\t\t\t\t\t\t\t\n\t\t\t\t\t\t\t\n\n\t\t\t\t\t\t\t\n\t\t\t\t\t\t\t\t\n\t\t\t\t\t\t\t\t\n\t\t\t\t\t\t\t\t\n\t\t\t\t\t\t\t\n\t\t                \t\n\t\t                \t\t\n\t\t                \t\t\t\tin   Kondapur \n\t\t                \t\t\n\t\t\t\t\t\t           \n\t         \t\t    \t\t\n\t\t           \t\t\t\n\t\t           \t\t\t\n                   "], "bhk": "\n\t\t\t            \t\t\n\t\t\t            \t\t\t\n\t\t\t            \t\t\t\t3 BHK Flat\n\t\t\t            \t\t\t\n\t\t\t            \t\t\t\n\t\t\t            \t\t\n\t\t\t            \t\t\n\t\t\t            \t", "societyName": "Sumadhura Horizon", "moreData": [["super area", "2510\u00a0sqft"], ["status", "\n\t\t\t\t\t\t\t\tPossession by Mar '23\n\t\t\t\t\t\t\t"], ["transaction", "New Property"], ["furnishing", "Unfurnished"], ["bathroom", "3"]]}
]